finance_utils/__init__.py
finance_utils/exception.py
finance_utils/version.py
finance_utils/component/__init__.py
finance_utils/component/bar.py
finance_utils/component/candle.py
finance_utils/component/commission.py
finance_utils/component/date.py
finance_utils/component/digit.py
finance_utils/component/filter.py
finance_utils/component/fprint.py
finance_utils/component/local.py
finance_utils/component/log.py
finance_utils/component/pool.py
finance_utils/component/price.py
finance_utils/component/size.py
finance_utils/component/thread.py
finance_utils/digtal_currency/__init__.py
finance_utils/digtal_currency/candle_io.py
finance_utils/digtal_currency/instId.py
finance_utils-1.0.3.dev5.dist-info/METADATA
finance_utils-1.0.3.dev5.dist-info/WHEEL
finance_utils-1.0.3.dev5.dist-info/top_level.txt
finance_utils-1.0.3.dev5.dist-info/RECORD
