Metadata-Version: 2.1
Name: finance-utils
Version: 1.0.3.dev5
Summary: Financial Quantitative Analysis Toolkit
Home-page: https://github.com/pyted/finance_utils
Author: pyted
Author-email: pyted@outlook.com
License: MIT
Classifier: License :: OSI Approved :: MIT License
Classifier: Programming Language :: Python
Classifier: Programming Language :: Python :: 3
Classifier: Programming Language :: Python :: 3.6
Classifier: Programming Language :: Python :: Implementation :: CPython
Classifier: Programming Language :: Python :: Implementation :: PyPy
Requires-Python: >=3.6.0
Requires-Dist: pendulum
Requires-Dist: numpy
Requires-Dist: pandas
